[
    {
        "Timestamp": "2025-09-08T00:27:45.792000",
        "Apakah sudah memiliki akun UI Connect?": "Ya",
        "Apakah sudah memiliki akun DAMRI?": "Ya",
        "Nama Lengkap": "Ery Puspiartono",
        "Jenis Kelamin": "Laki-laki",
        "Fakultas/Jurusan/Angkatan": "Vokasi/ Produksi Media/ 2021",
        "NPM": 2106643192,
        "Nomor Telepon": "081585386204",
        "Email": "ery.puspiartono@gmail.com",
        "Bukti screenshot profil UI Connect terverifikasi": "https://drive.google.com/open?id=1Sq0NsTsqHGWaCWqpcEiHbn08czmVlBBg",
        "Bukti screenshot profil akun aplikasi DAMRI": "https://drive.google.com/open?id=1HF1kj2MpvHKxZEC5DI3VSZDF8_Qgi858"
    },
    {
        "Timestamp": "2025-09-08T00:27:45.792000",
        "Apakah sudah memiliki akun UI Connect?": "Ya",
        "Apakah sudah memiliki akun DAMRI?": "Ya",
        "Nama Lengkap": "SITI JULAEHA",
        "Jenis Kelamin": "Perempuan",
        "Fakultas/Jurusan/Angkatan": "Vokasi/ Produksi Media/ 2021",
        "NPM": 2106643192,
        "Nomor Telepon": "082186951428",
        "Email": "julaeha707@gmail.com",
        "Bukti screenshot profil UI Connect terverifikasi": "https://drive.google.com/open?id=1Sq0NsTsqHGWaCWqpcEiHbn08czmVlBBg",
        "Bukti screenshot profil akun aplikasi DAMRI": "https://drive.google.com/open?id=1HF1kj2MpvHKxZEC5DI3VSZDF8_Qgi858"
    }
]